MANIFEST.in
README.md
requirements.txt
setup.py
rqalpha_mod_futu/VERSION.txt
rqalpha_mod_futu/__init__.py
rqalpha_mod_futu/futu_broker_hk.py
rqalpha_mod_futu/futu_data_source.py
rqalpha_mod_futu/futu_event_source.py
rqalpha_mod_futu/futu_market_state.py
rqalpha_mod_futu/futu_position.py
rqalpha_mod_futu/futu_utils.py
rqalpha_mod_futu/mod.py
rqalpha_mod_futu/rqalpha_simulate_broker.py
rqalpha_mod_futu.egg-info/PKG-INFO
rqalpha_mod_futu.egg-info/SOURCES.txt
rqalpha_mod_futu.egg-info/dependency_links.txt
rqalpha_mod_futu.egg-info/not-zip-safe
rqalpha_mod_futu.egg-info/requires.txt
rqalpha_mod_futu.egg-info/top_level.txt